commit/__init__.py
commit/commit.py
commit/utils.py
commit/model/__init__.py
commit/model/diff_roberta.py
commit/model/model.py
commit-0.1.0.dist-info/METADATA
commit-0.1.0.dist-info/WHEEL
commit-0.1.0.dist-info/entry_points.txt
commit-0.1.0.dist-info/top_level.txt
commit-0.1.0.dist-info/RECORD
