Metadata-Version: 2.1
Name: commit
Version: 0.1.0
Summary: A tool that AI automatically recommends commit messages.
Home-page: https://github.com/graykode/commit-autosuggestions
Author: TaeHwan-Jung
Author-email: nlkey2022@gmail.com
License: Apache License, Version 2.0
Project-URL: Source Code, https://github.com/graykode/commit-autosuggestions
Platform: any
Requires-Python: >=3.5
Requires-Dist: click (>=7.1.2)
Requires-Dist: gitpython (>=3.1.7)
Requires-Dist: whatthepatch (>=1.0.0)
Requires-Dist: packaging (>=20.4)
